{
    "FlightInformation": {
        "Flights": {
            "Flight": [
                {
                    "Departure": {
                        "AirportCode": "STR",
                        "Scheduled": {
                            "Date": "2024-07-13",
                            "Time": "12:35"
                        },
                        "Actual": {
                            "Date": "2024-07-13",
                            "Time": "14:06"
                        },
                        "Terminal": {
                            "Name": "3",
                            "Gate": "321"
                        },
                        "Status": {
                            "Code": "DP",
                            "Description": "Flight Departed"
                        }
                    },
                    "Arrival": {
                        "AirportCode": "BER",
                        "Scheduled": {
                            "Date": "2024-07-13",
                            "Time": "13:45"
                        },
                        "Actual": {
                            "Date": "2024-07-13",
                            "Time": "15:12"
                        },
                        "Terminal": {
                            "Name": "1",
                            "Gate": "A32"
                        },
                        "Status": {
                            "Code": "LD",
                            "Description": "Flight Landed"
                        }
                    },
                    "MarketingCarrierList": {
                        "MarketingCarrier": {
                            "AirlineID": "LH",
                            "FlightNumber": "5395"
                        }
                    },
                    "OperatingCarrier": {
                        "AirlineID": "4X",
                        "FlightNumber": "8003"
                    },
                    "Equipment": {
                        "AircraftCode": "320"
                    },
                    "Status": {
                        "Code": "LD",
                        "Description": "Flight Landed"
                    }
                },
                {
                    "Departure": {
                        "AirportCode": "FRA",
                        "Scheduled": {
                            "Date": "2024-07-13",
                            "Time": "12:45"
                        },
                        "Actual": {
                            "Date": "2024-07-13",
                            "Time": "13:40"
                        },
                        "Terminal": {
                            "Name": "1",
                            "Gate": "A13"
                        },
                        "Status": {
                            "Code": "DP",
                            "Description": "Flight Departed"
                        }
                    },
                    "Arrival": {
                        "AirportCode": "BER",
                        "Scheduled": {
                            "Date": "2024-07-13",
                            "Time": "13:55"
                        },
                        "Actual": {
                            "Date": "2024-07-13",
                            "Time": "14:38"
                        },
                        "Terminal": {
                            "Name": "1",
                            "Gate": "B20"
                        },
                        "Status": {
                            "Code": "LD",
                            "Description": "Flight Landed"
                        }
                    },
                    "MarketingCarrierList": {
                        "MarketingCarrier": [
                            {
                                "AirlineID": "AC",
                                "FlightNumber": "9247"
                            },
                            {
                                "AirlineID": "TP",
                                "FlightNumber": "7702"
                            },
                            {
                                "AirlineID": "UA",
                                "FlightNumber": "8887"
                            }
                        ]
                    },
                    "OperatingCarrier": {
                        "AirlineID": "LH",
                        "FlightNumber": "184"
                    },
                    "Equipment": {
                        "AircraftCode": "32Q"
                    },
                    "Status": {
                        "Code": "LD",
                        "Description": "Flight Landed"
                    }
                },
                {
                    "Departure": {
                        "AirportCode": "VIE",
                        "Scheduled": {
                            "Date": "2024-07-13",
                            "Time": "13:10"
                        },
                        "Actual": {
                            "Date": "2024-07-13",
                            "Time": "13:45"
                        },
                        "Terminal": {
                            "Name": "3",
                            "Gate": "F07"
                        },
                        "Status": {
                            "Code": "DP",
                            "Description": "Flight Departed"
                        }
                    },
                    "Arrival": {
                        "AirportCode": "BER",
                        "Scheduled": {
                            "Date": "2024-07-13",
                            "Time": "14:20"
                        },
                        "Actual": {
                            "Date": "2024-07-13",
                            "Time": "14:45"
                        },
                        "Terminal": {
                            "Name": "1",
                            "Gate": "B17"
                        },
                        "Status": {
                            "Code": "LD",
                            "Description": "Flight Landed"
                        }
                    },
                    "OperatingCarrier": {
                        "AirlineID": "OS",
                        "FlightNumber": "229"
                    },
                    "Equipment": {
                        "AircraftCode": "321"
                    },
                    "Status": {
                        "Code": "LD",
                        "Description": "Flight Landed"
                    }
                },
                {
                    "Departure": {
                        "AirportCode": "BIA",
                        "Scheduled": {
                            "Date": "2024-07-13",
                            "Time": "13:05"
                        },
                        "Actual": {
                            "Date": "2024-07-13",
                            "Time": "13:16"
                        },
                        "Status": {
                            "Code": "DP",
                            "Description": "Flight Departed"
                        }
                    },
                    "Arrival": {
                        "AirportCode": "BER",
                        "Scheduled": {
                            "Date": "2024-07-13",
                            "Time": "15:00"
                        },
                        "Actual": {
                            "Date": "2024-07-13",
                            "Time": "14:55"
                        },
                        "Terminal": {
                            "Name": "1",
                            "Gate": "N01"
                        },
                        "Status": {
                            "Code": "LD",
                            "Description": "Flight Landed"
                        }
                    },
                    "OperatingCarrier": {
                        "AirlineID": "EW",
                        "FlightNumber": "8433"
                    },
                    "Equipment": {
                        "AircraftCode": "31D"
                    },
                    "Status": {
                        "Code": "LD",
                        "Description": "Flight Landed"
                    }
                },
                {
                    "Departure": {
                        "AirportCode": "LCA",
                        "Scheduled": {
                            "Date": "2024-07-13",
                            "Time": "12:00"
                        },
                        "Actual": {
                            "Date": "2024-07-13",
                            "Time": "12:12"
                        },
                        "Status": {
                            "Code": "DP",
                            "Description": "Flight Departed"
                        }
                    },
                    "Arrival": {
                        "AirportCode": "BER",
                        "Scheduled": {
                            "Date": "2024-07-13",
                            "Time": "15:05"
                        },
                        "Actual": {
                            "Date": "2024-07-13",
                            "Time": "14:53"
                        },
                        "Terminal": {
                            "Name": "1",
                            "Gate": "N02"
                        },
                        "Status": {
                            "Code": "LD",
                            "Description": "Flight Landed"
                        }
                    },
                    "OperatingCarrier": {
                        "AirlineID": "EW",
                        "FlightNumber": "8905"
                    },
                    "Equipment": {
                        "AircraftCode": "21N"
                    },
                    "Status": {
                        "Code": "LD",
                        "Description": "Flight Landed"
                    }
                },
                {
                    "Departure": {
                        "AirportCode": "MUC",
                        "Scheduled": {
                            "Date": "2024-07-13",
                            "Time": "14:00"
                        },
                        "Actual": {
                            "Date": "2024-07-13",
                            "Time": "14:37"
                        },
                        "Terminal": {
                            "Name": "2",
                            "Gate": "G26"
                        },
                        "Status": {
                            "Code": "DP",
                            "Description": "Flight Departed"
                        }
                    },
                    "Arrival": {
                        "AirportCode": "BER",
                        "Scheduled": {
                            "Date": "2024-07-13",
                            "Time": "15:05"
                        },
                        "Actual": {
                            "Date": "2024-07-13",
                            "Time": "15:36"
                        },
                        "Terminal": {
                            "Name": "1",
                            "Gate": "B06"
                        },
                        "Status": {
                            "Code": "LD",
                            "Description": "Flight Landed"
                        }
                    },
                    "MarketingCarrierList": {
                        "MarketingCarrier": [
                            {
                                "AirlineID": "AC",
                                "FlightNumber": "9322"
                            },
                            {
                                "AirlineID": "TP",
                                "FlightNumber": "7520"
                            }
                        ]
                    },
                    "OperatingCarrier": {
                        "AirlineID": "LH",
                        "FlightNumber": "1942"
                    },
                    "Equipment": {
                        "AircraftCode": "32A"
                    },
                    "Status": {
                        "Code": "LD",
                        "Description": "Flight Landed"
                    }
                },
                {
                    "Departure": {
                        "AirportCode": "ZTH",
                        "Scheduled": {
                            "Date": "2024-07-13",
                            "Time": "14:30"
                        },
                        "Actual": {
                            "Date": "2024-07-13",
                            "Time": "15:17"
                        },
                        "Status": {
                            "Code": "DP",
                            "Description": "Flight Departed"
                        }
                    },
                    "Arrival": {
                        "AirportCode": "BER",
                        "Scheduled": {
                            "Date": "2024-07-13",
                            "Time": "16:20"
                        },
                        "Actual": {
                            "Date": "2024-07-13",
                            "Time": "16:53"
                        },
                        "Terminal": {
                            "Name": "1",
                            "Gate": "S02"
                        },
                        "Status": {
                            "Code": "LD",
                            "Description": "Flight Landed"
                        }
                    },
                    "OperatingCarrier": {
                        "AirlineID": "4X",
                        "FlightNumber": "8681"
                    },
                    "Equipment": {
                        "AircraftCode": "320"
                    },
                    "Status": {
                        "Code": "LD",
                        "Description": "Flight Landed"
                    }
                },
                {
                    "Departure": {
                        "AirportCode": "FRA",
                        "Scheduled": {
                            "Date": "2024-07-13",
                            "Time": "15:45"
                        },
                        "Actual": {
                            "Date": "2024-07-13",
                            "Time": "16:31"
                        },
                        "Terminal": {
                            "Name": "1",
                            "Gate": "A20"
                        },
                        "Status": {
                            "Code": "DP",
                            "Description": "Flight Departed"
                        }
                    },
                    "Arrival": {
                        "AirportCode": "BER",
                        "Scheduled": {
                            "Date": "2024-07-13",
                            "Time": "16:55"
                        },
                        "Actual": {
                            "Date": "2024-07-13",
                            "Time": "17:36"
                        },
                        "Terminal": {
                            "Name": "1",
                            "Gate": "B06"
                        },
                        "Status": {
                            "Code": "LD",
                            "Description": "Flight Landed"
                        }
                    },
                    "MarketingCarrierList": {
                        "MarketingCarrier": [
                            {
                                "AirlineID": "AC",
                                "FlightNumber": "9285"
                            },
                            {
                                "AirlineID": "CA",
                                "FlightNumber": "6091"
                            },
                            {
                                "AirlineID": "OU",
                                "FlightNumber": "5468"
                            },
                            {
                                "AirlineID": "TP",
                                "FlightNumber": "7704"
                            },
                            {
                                "AirlineID": "UA",
                                "FlightNumber": "8976"
                            }
                        ]
                    },
                    "OperatingCarrier": {
                        "AirlineID": "LH",
                        "FlightNumber": "190"
                    },
                    "Equipment": {
                        "AircraftCode": "321"
                    },
                    "Status": {
                        "Code": "LD",
                        "Description": "Flight Landed"
                    }
                },
                {
                    "Departure": {
                        "AirportCode": "MUC",
                        "Scheduled": {
                            "Date": "2024-07-13",
                            "Time": "16:00"
                        },
                        "Actual": {
                            "Date": "2024-07-13",
                            "Time": "17:00"
                        },
                        "Terminal": {
                            "Name": "2",
                            "Gate": "G18"
                        },
                        "Status": {
                            "Code": "DP",
                            "Description": "Flight Departed"
                        }
                    },
                    "Arrival": {
                        "AirportCode": "BER",
                        "Scheduled": {
                            "Date": "2024-07-13",
                            "Time": "17:05"
                        },
                        "Actual": {
                            "Date": "2024-07-13",
                            "Time": "18:02"
                        },
                        "Terminal": {
                            "Name": "1",
                            "Gate": "B10"
                        },
                        "Status": {
                            "Code": "LD",
                            "Description": "Flight Landed"
                        }
                    },
                    "MarketingCarrierList": {
                        "MarketingCarrier": [
                            {
                                "AirlineID": "AC",
                                "FlightNumber": "9530"
                            },
                            {
                                "AirlineID": "TP",
                                "FlightNumber": "7714"
                            },
                            {
                                "AirlineID": "UA",
                                "FlightNumber": "9107"
                            }
                        ]
                    },
                    "OperatingCarrier": {
                        "AirlineID": "LH",
                        "FlightNumber": "1946"
                    },
                    "Equipment": {
                        "AircraftCode": "32A"
                    },
                    "Status": {
                        "Code": "LD",
                        "Description": "Flight Landed"
                    }
                },
                {
                    "Departure": {
                        "AirportCode": "FRA",
                        "Scheduled": {
                            "Date": "2024-07-13",
                            "Time": "16:45"
                        },
                        "Actual": {
                            "Date": "2024-07-13",
                            "Time": "17:16"
                        },
                        "Terminal": {
                            "Name": "1",
                            "Gate": "A68"
                        },
                        "Status": {
                            "Code": "DP",
                            "Description": "Flight Departed"
                        }
                    },
                    "Arrival": {
                        "AirportCode": "BER",
                        "Scheduled": {
                            "Date": "2024-07-13",
                            "Time": "17:55"
                        },
                        "Actual": {
                            "Date": "2024-07-13",
                            "Time": "18:18"
                        },
                        "Terminal": {
                            "Name": "1",
                            "Gate": "B17"
                        },
                        "Status": {
                            "Code": "LD",
                            "Description": "Flight Landed"
                        }
                    },
                    "MarketingCarrierList": {
                        "MarketingCarrier": [
                            {
                                "AirlineID": "TP",
                                "FlightNumber": "7712"
                            },
                            {
                                "AirlineID": "UA",
                                "FlightNumber": "8715"
                            }
                        ]
                    },
                    "OperatingCarrier": {
                        "AirlineID": "LH",
                        "FlightNumber": "192"
                    },
                    "Equipment": {
                        "AircraftCode": "321"
                    },
                    "Status": {
                        "Code": "LD",
                        "Description": "Flight Landed"
                    }
                },
                {
                    "Departure": {
                        "AirportCode": "ZRH",
                        "Scheduled": {
                            "Date": "2024-07-13",
                            "Time": "16:30"
                        },
                        "Actual": {
                            "Date": "2024-07-13",
                            "Time": "16:46"
                        },
                        "Terminal": {
                            "Gate": "A73"
                        },
                        "Status": {
                            "Code": "DP",
                            "Description": "Flight Departed"
                        }
                    },
                    "Arrival": {
                        "AirportCode": "BER",
                        "Scheduled": {
                            "Date": "2024-07-13",
                            "Time": "17:55"
                        },
                        "Actual": {
                            "Date": "2024-07-13",
                            "Time": "18:01"
                        },
                        "Terminal": {
                            "Name": "1",
                            "Gate": "B20"
                        },
                        "Status": {
                            "Code": "LD",
                            "Description": "Flight Landed"
                        }
                    },
                    "OperatingCarrier": {
                        "AirlineID": "LX",
                        "FlightNumber": "970"
                    },
                    "Equipment": {
                        "AircraftCode": "320"
                    },
                    "Status": {
                        "Code": "LD",
                        "Description": "Flight Landed"
                    }
                },
                {
                    "Departure": {
                        "AirportCode": "BRU",
                        "Scheduled": {
                            "Date": "2024-07-13",
                            "Time": "16:30"
                        },
                        "Actual": {
                            "Date": "2024-07-13",
                            "Time": "16:36"
                        },
                        "Terminal": {
                            "Gate": "A48"
                        },
                        "Status": {
                            "Code": "DP",
                            "Description": "Flight Departed"
                        }
                    },
                    "Arrival": {
                        "AirportCode": "BER",
                        "Scheduled": {
                            "Date": "2024-07-13",
                            "Time": "17:55"
                        },
                        "Actual": {
                            "Date": "2024-07-13",
                            "Time": "17:52"
                        },
                        "Terminal": {
                            "Gate": "Y03"
                        },
                        "Status": {
                            "Code": "LD",
                            "Description": "Flight Landed"
                        }
                    },
                    "OperatingCarrier": {
                        "AirlineID": "SN",
                        "FlightNumber": "2587"
                    },
                    "Equipment": {
                        "AircraftCode": "319"
                    },
                    "Status": {
                        "Code": "LD",
                        "Description": "Flight Landed"
                    }
                }
            ]
        },
        "Meta": {
            "@Version": "1.0.0",
            "Link": [
                {
                    "@Href": "https://api.lufthansa.com/v1/operations/customerflightinformation/arrivals/BER/2024-07-13T14:00?limit=100",
                    "@Rel": "self"
                },
                {
                    "@Href": "https://api.lufthansa.com/v1/operations/customerflightinformation/arrivals/BER/2024-07-13T10:00?limit=50&offset=0",
                    "@Rel": "previousRange"
                },
                {
                    "@Href": "https://api.lufthansa.com/v1/operations/customerflightinformation/arrivals/BER/2024-07-13T18:00?limit=50&offset=0",
                    "@Rel": "nextRange"
                },
                {
                    "@Href": "https://api.lufthansa.com/v1/mds-references/airports/{airportCode}",
                    "@Rel": "related"
                }
            ],
            "TotalCount": 12
        }
    }
}